steamgamedata/__init__.py
steamgamedata/core.py
steamgamedata-1.1.0.dist-info/METADATA
steamgamedata-1.1.0.dist-info/WHEEL
steamgamedata-1.1.0.dist-info/top_level.txt
steamgamedata-1.1.0.dist-info/RECORD
