Metadata-Version: 2.1
Name: steamgamedata
Version: 1.1.0
Summary: A package to fetch and save game data from the Steam API.
Home-page: https://github.com/iamnotmega/steamgamedata
Author: NotMega
License: GNU General Public License v3.0
Classifier: Programming Language :: Python :: 3
Classifier: License :: OSI Approved :: GNU General Public License v3 (GPLv3)
Classifier: Operating System :: OS Independent
Requires-Python: >=3.6
Requires-Dist: requests
